<annotation>
	<folder>JPEGImages</folder>
	<filename>20211019_160241.jpg</filename>
	<path>C:\Users\user\Desktop\VOCdevkit\VOC2007\Annotations\20211019_160241.jpg</path>
	<source>
		<database>Unknown</database>
	</source>
	<size>
		<width>4032</width>
		<height>3024</height>
		<depth>3</depth>
	</size>
	<segmented>0</segmented>
	<object>
		<name>Mask</name>
		<pose>Unspecified</pose>
		<truncated>0</truncated>
		<difficult>0</difficult>
		<bndbox>
			<xmin>5</xmin>
			<ymin>1240</ymin>
			<xmax>605</xmax>
			<ymax>1637</ymax>
		</bndbox>
	</object>
	<object>
		<name>Mask</name>
		<pose>Unspecified</pose>
		<truncated>0</truncated>
		<difficult>0</difficult>
		<bndbox>
			<xmin>1464</xmin>
			<ymin>1318</ymin>
			<xmax>1927</xmax>
			<ymax>1643</ymax>
		</bndbox>
	</object>
	<object>
		<name>glasses</name>
		<pose>Unspecified</pose>
		<truncated>0</truncated>
		<difficult>0</difficult>
		<bndbox>
			<xmin>3458</xmin>
			<ymin>1062</ymin>
			<xmax>3811</xmax>
			<ymax>1177</ymax>
		</bndbox>
	</object>
	<object>
		<name>gloves</name>
		<pose>Unspecified</pose>
		<truncated>0</truncated>
		<difficult>0</difficult>
		<bndbox>
			<xmin>3805</xmin>
			<ymin>1827</ymin>
			<xmax>3993</xmax>
			<ymax>2018</ymax>
		</bndbox>
	</object>
	<object>
		<name>gloves</name>
		<pose>Unspecified</pose>
		<truncated>0</truncated>
		<difficult>0</difficult>
		<bndbox>
			<xmin>3636</xmin>
			<ymin>1862</ymin>
			<xmax>3833</xmax>
			<ymax>2087</ymax>
		</bndbox>
	</object>
	<object>
		<name>Face_Shield</name>
		<pose>Unspecified</pose>
		<truncated>1</truncated>
		<difficult>0</difficult>
		<bndbox>
			<xmin>3689</xmin>
			<ymin>1971</ymin>
			<xmax>4032</xmax>
			<ymax>2440</ymax>
		</bndbox>
	</object>
	<object>
		<name>Mask</name>
		<pose>Unspecified</pose>
		<truncated>0</truncated>
		<difficult>0</difficult>
		<bndbox>
			<xmin>2764</xmin>
			<ymin>1137</ymin>
			<xmax>3224</xmax>
			<ymax>1465</ymax>
		</bndbox>
	</object>
	<object>
		<name>Mask</name>
		<pose>Unspecified</pose>
		<truncated>0</truncated>
		<difficult>0</difficult>
		<bndbox>
			<xmin>3496</xmin>
			<ymin>1127</ymin>
			<xmax>3824</xmax>
			<ymax>1327</ymax>
		</bndbox>
	</object>
</annotation>